bandit_plugins/__init__.py
bandit_plugins/ban_network_requests.py
bandit_ban_network_requests-0.0.3.dist-info/AUTHORS
bandit_ban_network_requests-0.0.3.dist-info/METADATA
bandit_ban_network_requests-0.0.3.dist-info/WHEEL
bandit_ban_network_requests-0.0.3.dist-info/entry_points.txt
bandit_ban_network_requests-0.0.3.dist-info/top_level.txt
bandit_ban_network_requests-0.0.3.dist-info/RECORD
