Metadata-Version: 2.1
Name: bandit-ban-network-requests
Version: 0.0.3
Summary: Ban all network requests.
Author: Asad Iqbal
License-File: AUTHORS
Requires-Dist: bandit
